{
  "$schema": "https://developer.microsoft.com/json-schemas/fabric/item/report/definition/visualContainer/2.0.0/schema.json",
  "name": "visual018",
  "position": {
    "x": 340,
    "y": 20,
    "z": 18000,
    "height": 110,
    "width": 300,
    "tabOrder": 18000
  },
  "visual": {
    "visualType": "card",
    "query": {
      "queryState": {
        "Values": {
          "projections": [
            {
              "field": {
                "Measure": {
                  "Expression": {
                    "SourceRef": {
                      "Entity": "_Measures"
                    }
                  },
                  "Property": "Timing Diff Count"
                }
              },
              "queryRef": "_Measures.Timing Diff Count",
              "nativeQueryRef": "Timing Diff Count"
            }
          ]
        }
      }
    },
    "drillFilterOtherVisuals": true
  }
}
